README.rst
setup.py
Django_Pushy.egg-info/PKG-INFO
Django_Pushy.egg-info/SOURCES.txt
Django_Pushy.egg-info/dependency_links.txt
Django_Pushy.egg-info/pbr.json
Django_Pushy.egg-info/requires.txt
Django_Pushy.egg-info/top_level.txt
pushy/__init__.py
pushy/admin.py
pushy/apps.py
pushy/dispatchers.py
pushy/exceptions.py
pushy/models.py
pushy/tasks.py
pushy/utils.py
pushy/contrib/__init__.py
pushy/contrib/rest_api/__init__.py
pushy/contrib/rest_api/serializers.py
pushy/contrib/rest_api/urls.py
pushy/contrib/rest_api/views.py
pushy/migrations/0001_initial.py
pushy/migrations/0002_auto_20141011_1703.py
pushy/migrations/0003_auto_20150902_2001.py
pushy/migrations/0004_auto_20160220_1828.py
pushy/migrations/0005_auto_20160226_1946.py
pushy/migrations/__init__.py
tests/__init__.py
tests/conftest.py
tests/settings.py
tests/test_add_task.py
tests/test_api.py
tests/test_dispatchers.py
tests/test_tasks.py
tests/urls.py