Metadata-Version: 1.0
Name: Django-Pushy
Version: 1.0.1
Summary: Handle push notifications at scale.
Home-page: https://github.com/rakanalh/django-pushy
Author: Rakan Alhneiti
Author-email: rakan.alhneiti@gmail.com
License: LICENSE.txt
Platform: UNKNOWN
